pterodactyl/TransformToObject.py
pterodactyl/__init__.py
pterodactyl/API/Application.py
pterodactyl/API/Client.py
pterodactyl/API/__init__.py
pterodactyl/Objects/Consistent.py
pterodactyl/Objects/Errors.py
pterodactyl/Objects/Pagination.py
pterodactyl/Objects/Pterodactyl.py
pterodactyl/Objects/User.py
pterodactyl/Objects/__init__.py
pterodactyl-0.0.5.dist-info/LICENSE
pterodactyl-0.0.5.dist-info/METADATA
pterodactyl-0.0.5.dist-info/WHEEL
pterodactyl-0.0.5.dist-info/top_level.txt
pterodactyl-0.0.5.dist-info/RECORD
