Metadata-Version: 2.1
Name: pterodactyl
Version: 0.0.5
Summary: A Python wrapper for the Pterodactyl API.
Home-page: https://github.com/ItsTato/PterodactylPy
Author: ItsTato
Author-email: thatpogcomputer@gmail.com
Classifier: Programming Language :: Python :: 3
Classifier: Development Status :: 3 - Alpha
Classifier: Intended Audience :: Developers
Classifier: License :: OSI Approved :: BSD License
Classifier: Operating System :: OS Independent
Requires-Python: >=3.10
License-File: LICENSE
Requires-Dist: requests>=2.32.3
